{
    "idBook" : 2,
    "Title" : "Book 2",
    "Author" : "Author 2",
    "Editor" : "Editor 2",
    "Genre" : "Genre 2",
    "Chapters" : [
        {
            "ChapterNum" : 1,
            "Pages" :[
                {
                    "PageNum" : 1,
                    "pathPage" : "../books/book/pages/page02_01.md"
                },
                {
                    "PageNum" : 2,
                    "pathPage" : "../books/book/pages/page02_02.md"
                }
            ]
        }

    ]
}